pyModis-2.4.1.data/scripts/modis_check.py
pyModis-2.4.1.data/scripts/modis_convert.py
pyModis-2.4.1.data/scripts/modis_download.py
pyModis-2.4.1.data/scripts/modis_download_from_list.py
pyModis-2.4.1.data/scripts/modis_mosaic.py
pyModis-2.4.1.data/scripts/modis_multiparse.py
pyModis-2.4.1.data/scripts/modis_parse.py
pyModis-2.4.1.data/scripts/modis_quality.py
pymodis/__init__.py
pymodis/convertmodis.py
pymodis/convertmodis_gdal.py
pymodis/downmodis.py
pymodis/optparse_gui.py
pymodis/optparse_required.py
pymodis/parsemodis.py
pymodis/productmodis.py
pymodis/qualitymodis.py
pyModis-2.4.1.dist-info/AUTHORS
pyModis-2.4.1.dist-info/COPYING
pyModis-2.4.1.dist-info/METADATA
pyModis-2.4.1.dist-info/WHEEL
pyModis-2.4.1.dist-info/top_level.txt
pyModis-2.4.1.dist-info/RECORD
