Metadata-Version: 2.1
Name: pyModis
Version: 2.4.1
Summary: Python library for MODIS data
Home-page: http://www.pymodis.org
Author: Luca Delucchi
Author-email: luca.delucchi@fmach.it
License: GNU GPL 2 or later
Project-URL: Source, https://github.com/lucadelu/pyModis/
Project-URL: Tracker, https://github.com/lucadelu/pyModis/issues
Platform: Any
Classifier: Development Status :: 5 - Production/Stable
Classifier: Environment :: Console
Classifier: Topic :: Scientific/Engineering :: GIS
Classifier: Intended Audience :: End Users/Desktop
Classifier: Intended Audience :: Developers
Classifier: Operating System :: MacOS :: MacOS X
Classifier: Operating System :: Microsoft :: Windows
Classifier: Operating System :: POSIX
Classifier: Programming Language :: Python :: 2.7
Classifier: Programming Language :: Python :: 3
Classifier: License :: OSI Approved :: GNU General Public License v2 or later (GPLv2+)
License-File: COPYING
License-File: AUTHORS
Requires-Dist: numpy
Requires-Dist: future
Requires-Dist: requests
Requires-Dist: GDAL
Provides-Extra: gui
Requires-Dist: wxPython ; extra == 'gui'
Requires-Dist: wxPython-common ; extra == 'gui'
